{
  "title": "How to Build a Low-Waste Garden Routine",
  "slug": "how-to-build-a-low-waste-garden-routine",
  "excerpt": "A low-waste garden routine is built around simple habits that keep useful materials in the garden system instead of throwing them away. Composting, mulching, reusing organic matter, watering carefully, and choosing practical materials can all help reduce waste while improving soil and plant health.",
  "category": "Soil Health",
  "author": "Permatable Team",
  "published": true,
  "content": "<div class=\"article-callout\"><span class=\"eyebrow\">Low-Waste Gardening</span><p><strong>A low-waste garden does not happen because nothing is ever used. It happens because materials are used more thoughtfully, reused when possible, and returned to the system in useful ways.</strong> Instead of sending leaves, trimmings, kitchen scraps, and other organic matter away, a low-waste garden turns many of those materials into compost, mulch, soil improvement, or long-term garden value.</p></div><p>For most home gardeners, low-waste gardening is not about perfection. It is about building better routines. A few simple habits can reduce what leaves the garden, reduce what has to be bought, and strengthen the health of the soil at the same time.</p><h2>What a Low-Waste Garden Routine Means</h2><p>A low-waste garden routine means organizing your regular gardening habits so fewer useful materials are discarded unnecessarily.</p><p>In practice, that often includes:</p><ul><li>composting organic scraps</li><li>reusing leaves and trimmings</li><li>mulching instead of bagging everything away</li><li>buying fewer disposable inputs</li><li>watering more efficiently</li><li>using what the garden already produces</li></ul><p>The goal is not to create zero waste instantly. The goal is to make the garden more circular and less dependent on constant replacement.</p><h2>Why Low-Waste Gardening Matters</h2><p>Reducing waste in the garden has benefits far beyond tidiness.</p><p>It can help:</p><ul><li>build healthier soil</li><li>reduce disposal needs</li><li>save money over time</li><li>support long-term fertility</li><li>make the garden more sustainable</li></ul><p>Many materials that seem like waste are actually resources in the wrong place.</p><h2>Start With Composting</h2><p>Composting is one of the most important low-waste gardening habits because it turns everyday organic leftovers into a useful soil-building material.</p><p>You can often compost:</p><ul><li>fruit and vegetable scraps</li><li>coffee grounds</li><li>eggshells</li><li>dry leaves</li><li>yard trimmings</li><li>plain cardboard and paper</li></ul><p>Instead of sending those materials away, compost returns them to the garden in a far more useful form.</p><h2>Use Leaves as a Resource, Not a Burden</h2><p>Leaves are one of the easiest low-waste resources available to gardeners.</p><p>They can be used as:</p><ul><li>mulch</li><li>compost browns</li><li>leaf mold material</li><li>soil-building organic matter</li></ul><p>Rather than treating fall leaves as something to bag and remove, a low-waste routine treats them as future fertility and soil protection.</p><h2>Reuse Garden Trimmings Where Appropriate</h2><p>Many healthy garden trimmings can be reused instead of discarded.</p><p>Depending on the material, they may be suitable for:</p><ul><li>composting</li><li>rough mulch</li><li>chop-and-drop style surface feeding in some systems</li><li>filling compost layers with useful biomass</li></ul><p>This keeps organic matter moving within the garden instead of leaving the site unnecessarily.</p><h2>Mulch More, Throw Away Less</h2><p>Mulch is one of the best ways to use natural materials more efficiently.</p><p>It helps you make use of:</p><ul><li>leaves</li><li>shredded plant material</li><li>compost</li><li>straw</li><li>wood chips where appropriate</li></ul><p>At the same time, mulch reduces moisture loss, protects soil, and helps build organic matter over time. That means it lowers waste while improving the garden.</p><h2>Choose Reusable Materials When You Can</h2><p>A low-waste routine is not only about organic matter. It also includes avoiding unnecessary disposable materials.</p><p>This may mean using:</p><ul><li>durable pots and trays instead of one-season items</li><li>reusable plant labels</li><li>sturdy watering tools</li><li>compost bins or storage systems that last</li></ul><p>Small choices like these add up over time and reduce how much garden-related waste is created.</p><h2>Buy Only What the Garden Really Needs</h2><p>One easy way to reduce waste is to be more selective about what comes into the garden in the first place.</p><p>That can mean:</p><ul><li>buying fewer unnecessary products</li><li>choosing amendments with a clear purpose</li><li>avoiding decorative items that quickly become waste</li><li>using on-site materials first when they are suitable</li></ul><p>Low-waste gardening often starts with better decisions before anything enters the space.</p><h2>Water Efficiently to Reduce Resource Waste</h2><p>Water waste is part of garden waste too. A low-waste garden routine usually includes more efficient watering habits.</p><p>Helpful practices include:</p><ul><li>watering early in the day</li><li>watering the soil rather than broad unused areas</li><li>using mulch to reduce evaporation</li><li>improving soil so it holds moisture longer</li></ul><p>Using water more efficiently supports both sustainability and plant health.</p><h2>Keep Soil Covered and Productive</h2><p>Leaving soil bare often leads to wasted potential. Moisture is lost faster, weeds move in, and the garden may need more correction later.</p><p>A low-waste routine often includes:</p><ul><li>mulching bare ground</li><li>using cover crops in empty beds</li><li>keeping living roots in the soil where possible</li></ul><p>This reduces wasted space while improving soil at the same time.</p><h2>Save Seed When Practical</h2><p>Saving seed is not required for a low-waste garden, but it can be a helpful practice when used realistically.</p><p>For suitable crops, saving seed can:</p><ul><li>reduce repeat purchasing</li><li>keep useful varieties in your system</li><li>make the garden more self-reliant over time</li></ul><p>It works best when you start simple rather than trying to save everything at once.</p><h2>Use Kitchen and Garden Waste Together Wisely</h2><p>Some of the most effective low-waste gardening routines combine kitchen and garden materials into one useful cycle.</p><p>For example:</p><ul><li>kitchen scraps become compost greens</li><li>leaves and cardboard become compost browns</li><li>finished compost goes back into the beds</li></ul><p>This kind of cycle is one of the clearest examples of low-waste gardening in practice.</p><h2>Separate Useful Waste From Unusable Waste</h2><p>Not everything should go back into the garden. Diseased plants, contaminated materials, and unsuitable packaging may need to be handled differently.</p><p>A good low-waste routine includes being selective. The idea is not to reuse everything blindly. It is to keep valuable materials in the system while avoiding those that could create problems.</p><h2>Build Habits Around the Seasons</h2><p>Low-waste gardening often works best when it follows seasonal patterns.</p><p>For example:</p><ul><li>spring may focus on compost use and mulch renewal</li><li>summer may focus on efficient watering and reusing trimmings</li><li>fall may focus on saving leaves and clearing beds thoughtfully</li><li>winter may focus on storing useful materials and planning better input use</li></ul><p>Seasonal routines make low-waste habits easier to maintain naturally.</p><h2>Low-Waste Gardening Also Saves Money</h2><p>Reducing waste often reduces spending too.</p><p>When you compost more, mulch with what you already have, and reuse useful materials, you often need less:</p><ul><li>bagged compost</li><li>bagged mulch</li><li>waste removal</li><li>disposable garden supplies</li></ul><p>This makes low-waste gardening practical as well as environmentally helpful.</p><h2>What a Simple Low-Waste Garden Routine Might Look Like</h2><p>A practical low-waste routine for a beginner might include:</p><ul><li>keeping a kitchen scrap compost container</li><li>saving leaves for compost or mulch</li><li>using compost on beds regularly</li><li>reusing healthy trimmings in the soil system</li><li>mulching all exposed soil</li><li>watering carefully instead of wasting water on runoff or evaporation</li></ul><p>That is already enough to make the garden function more efficiently.</p><h2>Common Mistakes to Avoid</h2><p>A few habits can make low-waste gardening harder than it needs to be.</p><ul><li><strong>Throwing away useful organic material:</strong> many garden leftovers still have value</li><li><strong>Buying too many quick-fix products:</strong> more inputs often mean more future waste</li><li><strong>Leaving soil bare:</strong> this wastes moisture and organic potential</li><li><strong>Trying to do everything perfectly:</strong> low-waste gardening works best as a gradual routine</li><li><strong>Reusing unsuitable materials:</strong> being low-waste should not create plant or soil problems</li></ul><h2>Final Thoughts</h2><p>Building a low-waste garden routine is really about paying closer attention to what the garden already produces and what it actually needs. Composting, mulching, reusing leaves and trimmings, watering more wisely, and choosing durable materials all help reduce waste while improving soil and plant health.</p><p>You do not need a perfect closed-loop system to make progress. Even a few steady habits can turn everyday garden waste into something useful and make the whole garden more efficient over time.</p>"
}
