{
  "title": "Organic Mulches Compared: Which One Should You Choose?",
  "slug": "organic-mulches-compared-which-one-should-you-choose",
  "excerpt": "Organic mulches all help protect the soil, but they do not work in exactly the same way. Some break down quickly, some last longer, some feed the soil faster, and some are better for paths, vegetables, or perennial beds. The best mulch depends on what your garden needs most.",
  "category": "Soil Health",
  "author": "Permatable Team",
  "published": true,
  "content": "<div class=\"article-callout\"><span class=\"eyebrow\">Organic Mulches Compared</span><p><strong>Organic mulch is one of the best tools for improving soil health, but not all mulches behave the same way.</strong> Some are quick and nutrient-rich. Others are slower, coarser, and longer lasting. Choosing the right one depends on where you plan to use it, how quickly you want it to break down, and what kind of protection or soil-building effect you want most.</p></div><p>The good news is that many organic mulches are useful. The key is understanding their strengths rather than looking for one perfect mulch for every part of the garden.</p><h2>Why Organic Mulch Matters</h2><p>Organic mulch protects the soil while also contributing to it over time.</p><p>Most organic mulches help by:</p><ul><li>reducing moisture loss</li><li>protecting against erosion</li><li>moderating soil temperature</li><li>reducing weed pressure</li><li>adding organic matter as they break down</li></ul><p>That combination of protection and long-term soil feeding is what makes organic mulch so valuable.</p><h2>What Makes Mulches Different From One Another</h2><p>Different mulches vary in:</p><ul><li>how fast they break down</li><li>how long they stay in place</li><li>how rich or coarse they are</li><li>how well they suit vegetables, trees, or paths</li><li>how much immediate soil-feeding they provide</li></ul><p>Some mulches are better for quick soil improvement, while others are better for long-lasting surface cover.</p><h2>Compost as Mulch</h2><p>Finished compost works very well as a fine mulch, especially in vegetable gardens and beds where soil improvement is a top priority.</p><p><strong>Best for:</strong></p><ul><li>vegetable beds</li><li>seedling areas</li><li>top-dressing around productive crops</li><li>beds needing fast organic improvement</li></ul><p><strong>Main strengths:</strong></p><ul><li>adds organic matter quickly</li><li>feeds the soil directly</li><li>supports microbial life</li><li>looks neat and is easy to spread</li></ul><p><strong>Main limitation:</strong></p><ul><li>breaks down relatively quickly and usually does not last as long as coarser mulches</li></ul><h2>Shredded Leaves</h2><p>Shredded leaves are one of the best low-cost mulches for many home gardens.</p><p><strong>Best for:</strong></p><ul><li>vegetable beds</li><li>perennial borders</li><li>general soil-building</li><li>gardeners who want a free local mulch source</li></ul><p><strong>Main strengths:</strong></p><ul><li>easy to source in fall</li><li>good for soil improvement</li><li>break down into valuable organic matter</li><li>light enough for many garden uses</li></ul><p><strong>Main limitation:</strong></p><ul><li>whole unshredded leaves can mat if used too thickly</li></ul><h2>Straw</h2><p>Straw is a popular mulch for food gardens because it is light, easy to spread, and good at covering bare soil.</p><p><strong>Best for:</strong></p><ul><li>vegetable gardens</li><li>paths between rows</li><li>summer moisture retention</li><li>plants that benefit from clean fruit contact, such as strawberries</li></ul><p><strong>Main strengths:</strong></p><ul><li>good moisture protection</li><li>light and easy to handle</li><li>works well around many edible crops</li></ul><p><strong>Main limitation:</strong></p><ul><li>can break down fairly quickly and may need refreshing</li></ul><h2>Wood Chips</h2><p>Wood chips are one of the longest-lasting organic mulches and are especially useful around trees, shrubs, and perennial plantings.</p><p><strong>Best for:</strong></p><ul><li>fruit trees</li><li>shrubs</li><li>perennial beds</li><li>paths</li><li>long-term mulch coverage</li></ul><p><strong>Main strengths:</strong></p><ul><li>long-lasting</li><li>excellent surface protection</li><li>good for weed suppression</li><li>ideal for larger permanent planting areas</li></ul><p><strong>Main limitation:</strong></p><ul><li>usually slower to feed the soil than finer materials like compost</li></ul><h2>Leaf Mold</h2><p>Leaf mold is partly or fully decomposed leaf material and is especially valued for soil conditioning and moisture retention.</p><p><strong>Best for:</strong></p><ul><li>soil improvement</li><li>moisture-sensitive beds</li><li>woodland-style or perennial plantings</li><li>gardeners with access to lots of leaves</li></ul><p><strong>Main strengths:</strong></p><ul><li>excellent for holding moisture</li><li>good for improving texture</li><li>valuable for long-term soil health</li></ul><p><strong>Main limitation:</strong></p><ul><li>takes time to make if you are creating it yourself</li></ul><h2>Grass Clippings</h2><p>Grass clippings can be used as mulch, but they need some care.</p><p><strong>Best for:</strong></p><ul><li>thin mulch layers</li><li>quick surface cover</li><li>gardeners who want to reuse fresh yard material</li></ul><p><strong>Main strengths:</strong></p><ul><li>easy to access in many home gardens</li><li>break down quickly</li><li>return nutrients and organic matter rapidly</li></ul><p><strong>Main limitation:</strong></p><ul><li>can mat, smell, or become slimy if applied too thickly</li></ul><p>They work best in thin layers or mixed with drier materials.</p><h2>Pine Needles</h2><p>Pine needles can be a useful mulch in some gardens, especially where a lighter, airy cover is helpful.</p><p><strong>Best for:</strong></p><ul><li>ornamental beds</li><li>acid-loving plants where appropriate</li><li>sloped areas where needles interlock well</li></ul><p><strong>Main strengths:</strong></p><ul><li>lightweight</li><li>good air flow</li><li>less likely to compact heavily</li></ul><p><strong>Main limitation:</strong></p><ul><li>not always available in large amounts unless local to your site</li></ul><h2>Shredded Bark</h2><p>Shredded bark is often used in ornamental and perennial plantings where a tidy appearance and longer-lasting cover are important.</p><p><strong>Best for:</strong></p><ul><li>shrub borders</li><li>ornamental beds</li><li>long-lasting decorative mulch</li></ul><p><strong>Main strengths:</strong></p><ul><li>attractive appearance</li><li>good weed suppression</li><li>slower breakdown</li></ul><p><strong>Main limitation:</strong></p><ul><li>usually less useful than compost or leaf-based materials if your main goal is quick soil feeding in vegetable beds</li></ul><h2>Which Mulch Is Best for Vegetable Gardens?</h2><p>For most vegetable gardens, the best options are often:</p><ul><li>compost</li><li>shredded leaves</li><li>straw</li><li>light layers of grass clippings used carefully</li></ul><p>These mulches protect the soil while also supporting active, frequently managed growing beds.</p><h2>Which Mulch Is Best for Trees and Shrubs?</h2><p>For trees and shrubs, longer-lasting mulches usually work best.</p><p>Common good choices include:</p><ul><li>wood chips</li><li>shredded bark</li><li>leaf mold in some situations</li></ul><p>These materials help protect the root zone for longer periods and are well suited to less frequently disturbed plantings.</p><h2>Which Mulch Is Best for Fast Soil Improvement?</h2><p>If your main goal is to improve the soil quickly, finer organic mulches tend to help most.</p><p>Best choices often include:</p><ul><li>compost</li><li>shredded leaves</li><li>leaf mold</li><li>light nutrient-rich organic residues used appropriately</li></ul><p>These materials break down faster and feed the soil more directly.</p><h2>Free vs Purchased Mulches</h2><p>One of the best things about organic mulch is that some of the most useful options are often available for little or no cost.</p><p>Free or low-cost mulches may include:</p><ul><li>fallen leaves</li><li>homemade compost</li><li>grass clippings</li><li>locally available chipped branches</li></ul><p>Purchased mulches can still be useful, especially for appearance or convenience, but many gardeners can build healthier soil largely from materials already available around them.</p><h2>How to Choose the Right Mulch</h2><p>A practical way to choose is to ask:</p><ul><li>Do I need quick soil feeding or long-lasting surface cover?</li><li>Is this for vegetables, trees, or ornamental beds?</li><li>Do I need stronger moisture retention, weed suppression, or appearance?</li><li>What materials are already available to me?</li></ul><p>The best mulch is often the one that suits the bed and the purpose, not the one that sounds best in general.</p><h2>Common Mistakes to Avoid</h2><p>A few habits can make even a good mulch less effective.</p><ul><li><strong>Using the same mulch everywhere:</strong> different beds benefit from different materials</li><li><strong>Applying clippings too thickly:</strong> they can mat and smell</li><li><strong>Leaving mulch piled against stems or trunks:</strong> this can create moisture problems</li><li><strong>Ignoring breakdown speed:</strong> some mulches need refreshing sooner than others</li><li><strong>Choosing only by appearance:</strong> function matters too</li></ul><h2>Final Thoughts</h2><p>Organic mulches all help protect soil, but they differ in how quickly they break down, how long they last, and how well they suit different parts of the garden. Compost, leaves, straw, wood chips, bark, leaf mold, and other organic mulches each have strengths depending on the situation.</p><p>The best mulch is the one that fits your garden's actual needs. When you choose mulch with purpose, you protect the soil more effectively and build a healthier, more resilient garden over time.</p>"
}
